<?xml version="1.0" encoding="UTF-8"?>
<objects serializationModel="Studio.02.02.00">
	<object class="AudioFile" id="{178d76f5-9509-4e2a-948c-34bf47449145}">
		<property name="assetPath">
			<value>Footsteps - Essentials/Footsteps_Snow/Footsteps_Snow_Jump/Footsteps_Snow_Jump_Land_02.wav</value>
		</property>
		<property name="frequencyInKHz">
			<value>48</value>
		</property>
		<property name="channelCount">
			<value>1</value>
		</property>
		<property name="length">
			<value>0.40729166666666666</value>
		</property>
		<relationship name="masterAssetFolder">
			<destination>{5d06693b-a935-4042-93d9-739ec9be8bd5}</destination>
		</relationship>
	</object>
</objects>
